numopspy.py
numopspy-1.0.0.dist-info/LICENSE
numopspy-1.0.0.dist-info/METADATA
numopspy-1.0.0.dist-info/WHEEL
numopspy-1.0.0.dist-info/top_level.txt
numopspy-1.0.0.dist-info/RECORD
