Metadata-Version: 2.1
Name: numopspy
Version: 1.0.0
Summary: A comprehensive numerical operations library in pure Python
Author: Sai Pavan Velidandla
Author-email: connectwithpavan@gmail.com
License: MIT
Classifier: Programming Language :: Python :: 3
Classifier: License :: OSI Approved :: MIT License
Classifier: Operating System :: OS Independent
Requires-Python: >=3.6
License-File: LICENSE
